agensgraph4jupyter/__init__.py
agensgraph4jupyter/agensgraph4jupyter.py
agensgraph4jupyter/assets/index.html
agensgraph4jupyter-0.1.1.dist-info/DESCRIPTION.rst
agensgraph4jupyter-0.1.1.dist-info/METADATA
agensgraph4jupyter-0.1.1.dist-info/RECORD
agensgraph4jupyter-0.1.1.dist-info/WHEEL
agensgraph4jupyter-0.1.1.dist-info/metadata.json
agensgraph4jupyter-0.1.1.dist-info/top_level.txt
