Metadata-Version: 2.0
Name: agensgraph4jupyter
Version: 0.1.1
Summary: An agensgraph visualizer for Jupyter
Home-page: https://github.com/iomedhealth/agensgraph4jupyter
Author: Gabriel de Maeztu
Author-email: gabriel.maeztu@iomed.es
License: MIT
Keywords: jupyter agensgraph graphdb
Platform: UNKNOWN
Classifier: Development Status :: 4 - Beta
Classifier: Intended Audience :: Science/Research
Classifier: Topic :: Scientific/Engineering :: Visualization
Classifier: License :: OSI Approved :: MIT License
Classifier: Programming Language :: Python :: 3.3
Classifier: Programming Language :: Python :: 3.4
Classifier: Programming Language :: Python :: 3.5
Requires-Dist: IPython (>=4.0.0)
Requires-Dist: agensgraph
